KubernetesHandbook/README.md
KubernetesHandbook/__init__.py
KubernetesHandbook/__main__.py
KubernetesHandbook/file.epub
KubernetesHandbook/index.html
KubernetesHandbook/css/__init__.py
KubernetesHandbook/css/annotations.css
KubernetesHandbook/css/main.css
KubernetesHandbook/css/normalize.css
KubernetesHandbook/css/popup.css
KubernetesHandbook/font/__init__.py
KubernetesHandbook/font/fontello.eot
KubernetesHandbook/font/fontello.svg
KubernetesHandbook/font/fontello.ttf
KubernetesHandbook/font/fontello.woff
KubernetesHandbook/img/__init__.py
KubernetesHandbook/img/annotator-glyph-sprite.png
KubernetesHandbook/img/annotator-icon-sprite.png
KubernetesHandbook/img/apple-touch-icon.png
KubernetesHandbook/img/cancelfullscreen.png
KubernetesHandbook/img/close.png
KubernetesHandbook/img/fullscreen.png
KubernetesHandbook/img/loader.gif
KubernetesHandbook/img/menu-icon.png
KubernetesHandbook/img/save.png
KubernetesHandbook/img/saved.png
KubernetesHandbook/img/settings-s.png
KubernetesHandbook/img/settings.png
KubernetesHandbook/img/star.png
KubernetesHandbook/js/__init__.py
KubernetesHandbook/js/epub.js
KubernetesHandbook/js/epub.min.js
KubernetesHandbook/js/epub.min.map
KubernetesHandbook/js/hooks.min.js
KubernetesHandbook/js/hooks.min.map
KubernetesHandbook/js/reader.js
KubernetesHandbook/js/reader.js.map
KubernetesHandbook/js/reader.min.js
KubernetesHandbook/js/reader.min.map
KubernetesHandbook/js/hooks/__init__.py
KubernetesHandbook/js/hooks/extensions/__init__.py
KubernetesHandbook/js/hooks/extensions/highlight.js
KubernetesHandbook/js/libs/__init__.py
KubernetesHandbook/js/libs/jquery.min.js
KubernetesHandbook/js/libs/localforage.min.js
KubernetesHandbook/js/libs/screenfull.js
KubernetesHandbook/js/libs/screenfull.min.js
KubernetesHandbook/js/libs/zip.min.js
KubernetesHandbook/js/plugins/__init__.py
KubernetesHandbook/js/plugins/hypothesis.js
KubernetesHandbook/js/plugins/search.js
kubernetes_handbook-2024.3.2.0.dist-info/METADATA
kubernetes_handbook-2024.3.2.0.dist-info/WHEEL
kubernetes_handbook-2024.3.2.0.dist-info/entry_points.txt
kubernetes_handbook-2024.3.2.0.dist-info/top_level.txt
kubernetes_handbook-2024.3.2.0.dist-info/RECORD
